deepomatic_cli-0.7.7-py3.8-nspkg.pth
deepomatic/cli/__init__.py
deepomatic/cli/__main__.py
deepomatic/cli/cli_parser.py
deepomatic/cli/common.py
deepomatic/cli/exceptions.py
deepomatic/cli/frame.py
deepomatic/cli/input_data.py
deepomatic/cli/json_schema.py
deepomatic/cli/output_data.py
deepomatic/cli/thread_base.py
deepomatic/cli/version.py
deepomatic/cli/cmds/__init__.py
deepomatic/cli/cmds/parser_helpers.py
deepomatic/cli/cmds/utils.py
deepomatic/cli/cmds/platform/__init__.py
deepomatic/cli/cmds/platform/add_images.py
deepomatic/cli/cmds/platform/utils.py
deepomatic/cli/cmds/platform/drive_app/__init__.py
deepomatic/cli/cmds/platform/drive_app/create.py
deepomatic/cli/cmds/platform/drive_app/delete.py
deepomatic/cli/cmds/platform/drive_app/update.py
deepomatic/cli/cmds/platform/drive_app_version/__init__.py
deepomatic/cli/cmds/platform/drive_app_version/create.py
deepomatic/cli/cmds/platform/drive_app_version/delete.py
deepomatic/cli/cmds/platform/drive_app_version/update.py
deepomatic/cli/cmds/platform/engage_app/__init__.py
deepomatic/cli/cmds/platform/engage_app/create.py
deepomatic/cli/cmds/platform/engage_app/delete.py
deepomatic/cli/cmds/platform/engage_app_version/__init__.py
deepomatic/cli/cmds/platform/engage_app_version/create.py
deepomatic/cli/cmds/platform/engage_app_version/create_from.py
deepomatic/cli/cmds/platform/engage_app_version/delete.py
deepomatic/cli/cmds/platform/model/__init__.py
deepomatic/cli/cmds/platform/model/blur.py
deepomatic/cli/cmds/platform/model/draw.py
deepomatic/cli/cmds/platform/model/infer.py
deepomatic/cli/cmds/platform/model/noop.py
deepomatic/cli/cmds/site/__init__.py
deepomatic/cli/cmds/site/create.py
deepomatic/cli/cmds/site/delete.py
deepomatic/cli/cmds/site/install.py
deepomatic/cli/cmds/site/list.py
deepomatic/cli/cmds/site/load.py
deepomatic/cli/cmds/site/manifest.py
deepomatic/cli/cmds/site/rollback.py
deepomatic/cli/cmds/site/save.py
deepomatic/cli/cmds/site/show.py
deepomatic/cli/cmds/site/uninstall.py
deepomatic_cli-0.7.7.dist-info/LICENSE
deepomatic_cli-0.7.7.dist-info/METADATA
deepomatic_cli-0.7.7.dist-info/WHEEL
deepomatic_cli-0.7.7.dist-info/entry_points.txt
deepomatic_cli-0.7.7.dist-info/namespace_packages.txt
deepomatic_cli-0.7.7.dist-info/top_level.txt
deepomatic_cli-0.7.7.dist-info/RECORD
