Metadata-Version: 2.1
Name: deepomatic-cli
Version: 0.7.7
Summary: Deepomatic CLI
Home-page: https://github.com/Deepomatic/deepocli
Author: deepomatic
Author-email: support@deepomatic.com
License: MIT License
Platform: UNKNOWN
Classifier: Operating System :: OS Independent
Classifier: Programming Language :: Python
Classifier: Programming Language :: Python :: 3.6
Classifier: Programming Language :: Python :: 3.7
Classifier: Programming Language :: Python :: 3.8
Classifier: Programming Language :: Python :: 3.9
Classifier: Programming Language :: Python :: 3.10
Requires-Python: >=3.6.*
License-File: LICENSE
Requires-Dist: opencv-python-headless (<4.3,>=3.4.8.29)
Requires-Dist: tqdm (==4.62.3)
Requires-Dist: requests (<3,>=2.19.0)
Requires-Dist: text-unidecode (==1.3)
Requires-Dist: greenlet (<2,>=0.4.17)
Requires-Dist: gevent (<22.1,>=20.9.0)
Requires-Dist: jsonschema (==3.2.0)
Requires-Dist: deepomatic-api (==0.9.4)
Requires-Dist: PyYAML (>=3.12)
Requires-Dist: GitPython (<3.2.0,>=3.1.0)
Requires-Dist: argcomplete (<2,>=1.11.1)
Provides-Extra: rpc
Requires-Dist: deepomatic-rpc (>=0.8.0) ; extra == 'rpc'
